LICENSE
README.md
setup.py
hello_world/__init__.py
hello_world/main.py
sunrequests.egg-info/PKG-INFO
sunrequests.egg-info/SOURCES.txt
sunrequests.egg-info/dependency_links.txt
sunrequests.egg-info/top_level.txt