Metadata-Version: 2.1
Name: sunrequests
Version: 0.0.1
Summary: A Example package
Home-page: https://github.com/gokm5133/sample-pypi-package
Author: Lefo
Author-email: example@gmail.com
Classifier: Programming Language :: Python :: 3.8
Classifier: License :: OSI Approved :: MIT License
Classifier: Operating System :: OS Independent
Requires-Python: >=3.6
License-File: LICENSE
